HWIDLib.py
hwidlib-1.0.dist-info/LICENSE
hwidlib-1.0.dist-info/METADATA
hwidlib-1.0.dist-info/WHEEL
hwidlib-1.0.dist-info/RECORD
