Metadata-Version: 2.1
Name: HWIDLib
Version: 1.0
Summary: A library for getting or modifing hardware IDs on Windows
License: GPL-3.0
Author: Elias Tverfjell
Author-email: elias.tverfjell@gmail.com
Requires-Python: >=3.13,<4.0
Classifier: License :: OSI Approved :: GNU General Public License v3 (GPLv3)
Classifier: Operating System :: OS Independent
Classifier: Programming Language :: Python :: 3
Classifier: Programming Language :: Python :: 3.13
